pypremium/__init__.py
pypremium/pypremium.py
pypremium-1.0.3.dist-info/METADATA
pypremium-1.0.3.dist-info/WHEEL
pypremium-1.0.3.dist-info/license
pypremium-1.0.3.dist-info/top_level.txt
pypremium-1.0.3.dist-info/RECORD
